build/lib/build/lib/multimetric/__init__.py
build/lib/build/lib/multimetric/__main__.py
build/lib/build/lib/multimetric/cls/__init__.py
build/lib/build/lib/multimetric/cls/base.py
build/lib/build/lib/multimetric/cls/base_calc.py
build/lib/build/lib/multimetric/cls/base_stats.py
build/lib/build/lib/multimetric/cls/modules.py
build/lib/build/lib/multimetric/cls/tokentree.py
build/lib/build/lib/multimetric/cls/calc/__init__.py
build/lib/build/lib/multimetric/cls/calc/halstead.py
build/lib/build/lib/multimetric/cls/calc/maintenance.py
build/lib/build/lib/multimetric/cls/calc/pylint.py
build/lib/build/lib/multimetric/cls/calc/tiobe.py
build/lib/build/lib/multimetric/cls/importer/__init__.py
build/lib/build/lib/multimetric/cls/importer/base.py
build/lib/build/lib/multimetric/cls/importer/filtered.py
build/lib/build/lib/multimetric/cls/importer/pick.py
build/lib/build/lib/multimetric/cls/importer/mods/__init__.py
build/lib/build/lib/multimetric/cls/importer/mods/csv_importer.py
build/lib/build/lib/multimetric/cls/importer/mods/json_importer.py
build/lib/build/lib/multimetric/cls/metric/__init__.py
build/lib/build/lib/multimetric/cls/metric/comments.py
build/lib/build/lib/multimetric/cls/metric/cyclomatic.py
build/lib/build/lib/multimetric/cls/metric/fanout.py
build/lib/build/lib/multimetric/cls/metric/loc.py
build/lib/build/lib/multimetric/cls/metric/operands.py
build/lib/build/lib/multimetric/cls/metric/operators.py
build/lib/build/lib/multimetric/cls/stats/__init__.py
build/lib/build/lib/multimetric/cls/stats/stats.py
build/lib/multimetric/__init__.py
build/lib/multimetric/__main__.py
build/lib/multimetric/cls/__init__.py
build/lib/multimetric/cls/base.py
build/lib/multimetric/cls/base_calc.py
build/lib/multimetric/cls/base_stats.py
build/lib/multimetric/cls/modules.py
build/lib/multimetric/cls/tokentree.py
build/lib/multimetric/cls/calc/__init__.py
build/lib/multimetric/cls/calc/halstead.py
build/lib/multimetric/cls/calc/maintenance.py
multimetric-2.4.0.dist-info/licenses/LICENSE.Zlib
multimetric-2.4.0.dist-info/METADATA
multimetric-2.4.0.dist-info/WHEEL
multimetric-2.4.0.dist-info/entry_points.txt
multimetric-2.4.0.dist-info/top_level.txt
multimetric-2.4.0.dist-info/RECORD
