Metadata-Version: 2.4
Name: multimetric
Version: 2.4.0
Summary: Calculate code metrics in various languages
Maintainer-email: Konrad Weihmann <kweihmann@outlook.com>
License-Expression: Zlib
Project-URL: homepage, https://github.com/priv-kweihmann/multimetric
Project-URL: repository, https://github.com/priv-kweihmann/multimetric.git
Project-URL: bugtracker, https://github.com/priv-kweihmann/multimetric/issues
Classifier: Development Status :: 4 - Beta
Classifier: Environment :: Console
Classifier: Intended Audience :: Developers
Classifier: Natural Language :: English
Classifier: Operating System :: POSIX :: Linux
Classifier: Programming Language :: Python :: 3 :: Only
Classifier: Programming Language :: Python :: 3
Classifier: Programming Language :: Python :: 3.10
Classifier: Programming Language :: Python :: 3.11
Classifier: Programming Language :: Python :: 3.12
Classifier: Programming Language :: Python :: 3.13
Classifier: Programming Language :: Python :: 3.14
Classifier: Topic :: Software Development :: Quality Assurance
Requires-Python: >=3.10
License-File: LICENSE.Zlib
Requires-Dist: chardet~=5.2
Requires-Dist: pygments~=2.19
Provides-Extra: dev
Requires-Dist: Flake8-pyproject==1.2.3; extra == "dev"
Requires-Dist: bump-my-version==1.2.4; extra == "dev"
Requires-Dist: build==1.3.0; extra == "dev"
Requires-Dist: dlint==0.16.0; extra == "dev"
Requires-Dist: flake8==7.3.0; extra == "dev"
Requires-Dist: flake8-2020==1.8.1; extra == "dev"
Requires-Dist: flake8-broken-line==1.0.0; extra == "dev"
Requires-Dist: flake8-bugbear==24.12.12; extra == "dev"
Requires-Dist: flake8-builtins==3.0.0; extra == "dev"
Requires-Dist: flake8-coding==1.3.2; extra == "dev"
Requires-Dist: flake8-commas==4.0.0; extra == "dev"
Requires-Dist: flake8-comprehensions==3.17.0; extra == "dev"
Requires-Dist: flake8-debugger==4.1.2; extra == "dev"
Requires-Dist: flake8-docstrings==1.7.0; extra == "dev"
Requires-Dist: flake8-eradicate==1.5.0; extra == "dev"
Requires-Dist: flake8-executable==2.1.3; extra == "dev"
Requires-Dist: flake8-fixme==1.1.1; extra == "dev"
Requires-Dist: flake8-isort==6.1.2; extra == "dev"
Requires-Dist: flake8-mutable==1.2.0; extra == "dev"
Requires-Dist: flake8-pep3101==2.1.0; extra == "dev"
Requires-Dist: flake8-print==5.0.0; extra == "dev"
Requires-Dist: flake8-quotes==3.4.0; extra == "dev"
Requires-Dist: flake8-requirements==2.3.0; extra == "dev"
Requires-Dist: flake8-variables-names==0.0.6; extra == "dev"
Requires-Dist: pytest==8.4.2; extra == "dev"
Requires-Dist: pytest-cov==3.0.0; extra == "dev"
Requires-Dist: pytest-icdiff==0.9; extra == "dev"
Requires-Dist: pytest-parallel==0.1.1; extra == "dev"
Requires-Dist: pytest-random-order==1.2.0; extra == "dev"
Requires-Dist: pytest-socket==0.7.0; extra == "dev"
Requires-Dist: pytest-sugar==1.1.1; extra == "dev"
Requires-Dist: pytest-tldr==0.2.5; extra == "dev"
Requires-Dist: requests==2.32.5; extra == "dev"
Requires-Dist: twine==6.2.0; extra == "dev"
Dynamic: license-file
